Workbook

Sheet Modelo
A1: MODELO DE MÁRGENES — TIENDA ONLINE DE PERFUMES
A2: Proveedor: Star Company (Ciudad del Este, PY) · Precios de lista en USD · Costo de traída NO incluido (configurable abajo)
A4: SUPUESTOS (editar las celdas azules)
A5: Cotización USD → ARS | B5: 1300 | C5: Editar con el dólar real con el que se compra
A6: Costo de traída (%) | B6: 0 | C6: En 0 por ahora (no se considera). Cambiar cuando se defina
A7: Markup objetivo (x) | B7: 2.5 | C7: Multiplicador sobre el costo para el PVP sugerido
A9: Marca | B9: Producto | C9: ml | D9: Categoría | E9: Costo USD (lista) | F9: Costo ARS (c/ traída) | G9: PVP sugerido (ARS) | H9: Margen $ (ARS) | I9: Margen % | J9: Precio mercado AR (ref.) | K9: Comentario
A10: 12 Parfumeurs Français | B10: 12 PARFUMEURS FRANCAIS FONTAINEBLEAU EXDP 100ML UNISEX | C10: 100 | D10: Nicho | E10: 155 | F10: =E10*$B$5*(1+$B$6) -> 201500 | G10: =F10*$B$7 -> 503750 | H10: =G10-F10 -> 302250 | I10: =H10/G10 -> 0.6
A11: 12 Parfumeurs Français | B11: 12 PARFUMEURS FRANCAIS LUXEMBOURG EXDP 100ML UNISEX | C11: 100 | D11: Nicho | E11: 155 | F11: =E11*$B$5*(1+$B$6) -> 201500 | G11: =F11*$B$7 -> 503750 | H11: =G11-F11 -> 302250 | I11: =H11/G11 -> 0.6
A12: 12 Parfumeurs Français | B12: 12 PARFUMEURS FRANCAIS MADAME ROYALE EXDP 100ML UNISEX | C12: 100 | D12: Nicho | E12: 155 | F12: =E12*$B$5*(1+$B$6) -> 201500 | G12: =F12*$B$7 -> 503750 | H12: =G12-F12 -> 302250 | I12: =H12/G12 -> 0.6
A13: 12 Parfumeurs Français | B13: 12 PARFUMEURS FRANCAIS MALMAISON EXDP 100ML UNISEX | C13: 100 | D13: Nicho | E13: 155 | F13: =E13*$B$5*(1+$B$6) -> 201500 | G13: =F13*$B$7 -> 503750 | H13: =G13-F13 -> 302250 | I13: =H13/G13 -> 0.6
A14: 12 Parfumeurs Français | B14: 12 PARFUMEURS FRANCAIS PRAFRANCE EXDP 100ML UNISEX | C14: 100 | D14: Nicho | E14: 155 | F14: =E14*$B$5*(1+$B$6) -> 201500 | G14: =F14*$B$7 -> 503750 | H14: =G14-F14 -> 302250 | I14: =H14/G14 -> 0.6
A15: Afnan | B15: AFNAN 9AM DIVE EDP 100ML | C15: 100 | D15: Árabe | E15: 22.75 | F15: =E15*$B$5*(1+$B$6) -> 29575 | G15: =F15*$B$7 -> 73937.5 | H15: =G15-F15 -> 44362.5 | I15: =H15/G15 -> 0.6
A16: Afnan | B16: AFNAN 9AM DIVE EDP 150ML | C16: 150 | D16: Árabe | E16: 31 | F16: =E16*$B$5*(1+$B$6) -> 40300 | G16: =F16*$B$7 -> 100750 | H16: =G16-F16 -> 60450 | I16: =H16/G16 -> 0.6
A17: Afnan | B17: AFNAN 9PM (BLACK) EDP 150ML MASC | C17: 150 | D17: Árabe | E17: 31 | F17: =E17*$B$5*(1+$B$6) -> 40300 | G17: =F17*$B$7 -> 100750 | H17: =G17-F17 -> 60450 | I17: =H17/G17 -> 0.6
A18: Afnan | B18: AFNAN 9PM FEMME (PURPLE) EDP 100ML FEM | C18: 100 | D18: Árabe | E18: 22.25 | F18: =E18*$B$5*(1+$B$6) -> 28925 | G18: =F18*$B$7 -> 72312.5 | H18: =G18-F18 -> 43387.5 | I18: =H18/G18 -> 0.6
A19: Afnan | B19: AFNAN HISTORIC OLMEDA EDP 100ML | C19: 100 | D19: Árabe | E19: 23.75 | F19: =E19*$B$5*(1+$B$6) -> 30875 | G19: =F19*$B$7 -> 77187.5 | H19: =G19-F19 -> 46312.5 | I19: =H19/G19 -> 0.6
A20: Afnan | B20: AFNAN HISTORIC SAHARA EXTRAIT DE PARFUM 100ML | C20: 100 | D20: Árabe | E20: 28.5 | F20: =E20*$B$5*(1+$B$6) -> 37050 | G20: =F20*$B$7 -> 92625 | H20: =G20-F20 -> 55575 | I20: =H20/G20 -> 0.6
A21: Afnan | B21: AFNAN KIAANA ANGEL EDP 100ML FEMININO | C21: 100 | D21: Árabe | E21: 23.5 | F21: =E21*$B$5*(1+$B$6) -> 30550 | G21: =F21*$B$7 -> 76375 | H21: =G21-F21 -> 45825 | I21: =H21/G21 -> 0.6
... A37: Al Haramain | B37: AL HARAMAIN AMBER OUD ULTRA VIOLET EDP 120ML | C37: 120 | D37: Árabe | E37: 44 | F37: =E37*$B$5*(1+$B$6) -> 57200 | G37: =F37*$B$7 -> 143000 | H37: =G37-F37 -> 85800 | I37: =H37/G37 -> 0.6
A38: Al Haramain | B38: AL HARAMAIN AMBER OUD ULTRA VIOLET PERFUMERY GIFT SET WITH BODYMIST (7 | D38: Árabe | E38: 65 | F38: =E38*$B$5*(1+$B$6) -> 84500 | G38: =F38*$B$7 -> 211250 | H38: =G38-F38 -> 126750 | I38: =H38/G38 -> 0.6
A39: Al Haramain | B39: AL HARAMAIN AMBER OUD WHITE EDP 100ML | C39: 100 | D39: Árabe | E39: 31 | F39: =E39*$B$5*(1+$B$6) -> 40300 | G39: =F39*$B$7 -> 100750 | H39: =G39-F39 -> 60450 | I39: =H39/G39 -> 0.6
A40: Al Haramain | B40: AL HARAMAIN AVALON EDP 100ML | C40: 100 | D40: Árabe | E40: 28 | F40: =E40*$B$5*(1+$B$6) -> 36400 | G40: =F40*$B$7 -> 91000 | H40: =G40-F40 -> 54600 | I40: =H40/G40 -> 0.6
A41: Al Haramain | B41: AL HARAMAIN AZURE EDP 100ML | C41: 100 | D41: Árabe | E41: 28 | F41: =E41*$B$5*(1+$B$6) -> 36400 | G41: =F41*$B$7 -> 91000 | H41: =G41-F41 -> 54600 | I41: =H41/G41 -> 0.6
A42: Al Haramain | B42: AL HARAMAIN AZURE EDP 30ML | C42: 30 | D42: Árabe | E42: 11 | F42: =E42*$B$5*(1+$B$6) -> 14300 | G42: =F42*$B$7 -> 35750 | H42: =G42-F42 -> 21450 | I42: =H42/G42 -> 0.6
A43: Al Haramain | B43: AL HARAMAIN CONCEPTION EDP 100ML | C43: 100 | D43: Árabe | E43: 28 | F43: =E43*$B$5*(1+$B$6) -> 36400 | G43: =F43*$B$7 -> 91000 | H43: =G43-F43 -> 54600 | I43: =H43/G43 -> 0.6
A44: Al Haramain | B44: AL HARAMAIN CONCEPTION EDP 30ML | C44: 30 | D44: Árabe | E44: 11 | F44: =E44*$B$5*(1+$B$6) -> 14300 | G44: =F44*$B$7 -> 35750 | H44: =G44-F44 -> 21450 | I44: =H44/G44 -> 0.6
A45: Al Haramain | B45: AL HARAMAIN FLORAL FAIR EDP 100ML | C45: 100 | D45: Árabe | E45: 25 | F45: =E45*$B$5*(1+$B$6) -> 32500 | G45: =F45*$B$7 -> 81250 | H45: =G45-F45 -> 48750 | I45: =H45/G45 -> 0.6
A46: Al Haramain | B46: AL HARAMAIN FREYA EDP 100ML | C46: 100 | D46: Árabe | E46: 27 | F46: =E46*$B$5*(1+$B$6) -> 35100 | G46: =F46*$B$7 -> 87750 | H46: =G46-F46 -> 52650 | I46: =H46/G46 -> 0.6
A47: Al Haramain | B47: AL HARAMAIN FREYA EDP 30ML | C47: 30 | D47: Árabe | E47: 11 | F47: =E47*$B$5*(1+$B$6) -> 14300 | G47: =F47*$B$7 -> 35750 | H47: =G47-F47 -> 21450 | I47: =H47/G47 -> 0.6
A48: Al Haramain | B48: AL HARAMAIN GOLD CRYSTAL OUDH EXTRAIT DE PARFUM 100ML | C48: 100 | D48: Árabe | E48: 28.5 | F48: =E48*$B$5*(1+$B$6) -> 37050 | G48: =F48*$B$7 -> 92625 | H48: =G48-F48 -> 55575 | I48: =H48/G48 -> 0.6
A49: Al Haramain | B49: AL HARAMAIN GOLD CRYSTAL SAPHIRE 100ML | C49: 100 | D49: Árabe | E49: 28.5 | F49: =E49*$B$5*(1+$B$6) -> 37050 | G49: =F49*$B$7 -> 92625 | H49: =G49-F49 -> 55575 | I49: =H49/G49 -> 0.6
A50: Al Haramain | B50: AL HARAMAIN GREEN DUBAI EXTRAIT DE PARFUM 100ML | C50: 100 | D50: Árabe | E50: 25 | F50: =E50*$B$5*(1+$B$6) -> 32500 | G50: =F50*$B$7 -> 81250 | H50: =G50-F50 -> 48750 | I50: =H50/G50 -> 0.6
... A75: Al Haramain | B75: AL HARAMAIN SHEIKH MAJESTIC EXTRAIT DE PARFUM 100ML | C75: 100 | D75: Árabe | E75: 130 | F75: =E75*$B$5*(1+$B$6) -> 169000 | G75: =F75*$B$7 -> 422500 | H75: =G75-F75 -> 253500 | I75: =H75/G75 -> 0.6
A76: Al Haramain | B76: AL HARAMAIN SHEIKH PRESTIGE TRAVEL PACK WITH TUBE COVER + 4 TUBE BLACK | D76: Árabe | E76: 65 | F76: =E76*$B$5*(1+$B$6) -> 84500 | G76: =F76*$B$7 -> 211250 | H76: =G76-F76 -> 126750 | I76: =H76/G76 -> 0.6
A77: Al Haramain | B77: AL HARAMAIN SHEIKH PRESTIGE TRAVEL PACK WITH TUBE COVER + 4 TUBE BLUE | D77: Árabe | E77: 65 | F77: =E77*$B$5*(1+$B$6) -> 84500 | G77: =F77*$B$7 -> 211250 | H77: =G77-F77 -> 126750 | I77: =H77/G77 -> 0.6
A78: Al Haramain | B78: AL HARAMAIN SHEIKH PRESTIGE TRAVEL PACK WITH TUBE COVER + 4 TUBE GREEN | D78: Árabe | E78: 65 | F78: =E78*$B$5*(1+$B$6) -> 84500 | G78: =F78*$B$7 -> 211250 | H78: =G78-F78 -> 126750 | I78: =H78/G78 -> 0.6
A79: Al Haramain | B79: AL HARAMAIN SHEIKH PRESTIGE TRAVEL PACK WITH TUBE COVER + 4 TUBE RED | D79: Árabe | E79: 65 | F79: =E79*$B$5*(1+$B$6) -> 84500 | G79: =F79*$B$7 -> 211250 | H79: =G79-F79 -> 126750 | I79: =H79/G79 -> 0.6
A80: Al Haramain | B80: AL HARAMAIN SHEIKH ROYAL EXTRAIT DE PARFUM 100ML | C80: 100 | D80: Árabe | E80: 130 | F80: =E80*$B$5*(1+$B$6) -> 169000 | G80: =F80*$B$7 -> 422500 | H80: =G80-F80 -> 253500 | I80: =H80/G80 -> 0.6
A81: Al Haramain | B81: AL HARAMAIN SHEIKH WARRIOR EXTRAIT DE PARFUM 100ML | C81: 100 | D81: Árabe | E81: 130 | F81: =E81*$B$5*(1+$B$6) -> 169000 | G81: =F81*$B$7 -> 422500 | H81: =G81-F81 -> 253500 | I81: =H81/G81 -> 0.6
A82: Al Haramain | B82: AL HARAMAIN VERGINE ROSA EDP 100ML | C82: 100 | D82: Árabe | E82: 41 | F82: =E82*$B$5*(1+$B$6) -> 53300 | G82: =F82*$B$7 -> 133250 | H82: =G82-F82 -> 79950 | I82: =H82/G82 -> 0.6
A83: Al Wataniah | B83: AL WATANIAH AL DAIEM EDP 75ML | C83: 75 | D83: Árabe | E83: 23.5 | F83: =E83*$B$5*(1+$B$6) -> 30550 | G83: =F83*$B$7 -> 76375 | H83: =G83-F83 -> 45825 | I83: =H83/G83 -> 0.6
A84: Al Wataniah | B84: AL WATANIAH AL DAIEM ELIXIR EDP 75ML | C84: 75 | D84: Árabe | E84: 23.5 | F84: =E84*$B$5*(1+$B$6) -> 30550 | G84: =F84*$B$7 -> 76375 | H84: =G84-F84 -> 45825 | I84: =H84/G84 -> 0.6
A85: Al Wataniah | B85: AL WATANIAH AMEERATI EDP 100ML FEM | C85: 100 | D85: Árabe | E85: 11.99 | F85: =E85*$B$5*(1+$B$6) -> 15587 | G85: =F85*$B$7 -> 38967.5 | H85: =G85-F85 -> 23380.5 | I85: =H85/G85 -> 0.6
A86: Al Wataniah | B86: AL WATANIAH AMETHYST EDP 100ML | C86: 100 | D86: Árabe | E86: 9.75 | F86: =E86*$B$5*(1+$B$6) -> 12675 | G86: =F86*$B$7 -> 31687.5 | H86: =G86-F86 -> 19012.5 | I86: =H86/G86 -> 0.6
A87: Al Wataniah | B87: AL WATANIAH ATTAR AL WESAL GOLD EDP 100ML | C87: 100 | D87: Árabe | E87: 25 | F87: =E87*$B$5*(1+$B$6) -> 32500 | G87: =F87*$B$7 -> 81250 | H87: =G87-F87 -> 48750 | I87: =H87/G87 -> 0.6
A88: Al Wataniah | B88: AL WATANIAH DURRAT AL AROOS EDP 85ML | C88: 85 | D88: Árabe | E88: 12 | F88: =E88*$B$5*(1+$B$6) -> 15600 | G88: =F88*$B$7 -> 39000 | H88: =G88-F88 -> 23400 | I88: =H88/G88 -> 0.6
A89: Al Wataniah | B89: AL WATANIAH DURRAT AL AROOS LOVE EDP 85ML | C89: 85 | D89: Árabe | E89: 23.5 | F89: =E89*$B$5*(1+$B$6) -> 30550 | G89: =F89*$B$7 -> 76375 | H89: =G89-F89 -> 45825 | I89: =H89/G89 -> 0.6
A90: Al Wataniah | B90: AL WATANIAH ROWAN BLUSH EDP 100ML | C90: 100 | D90: Árabe | E90: 23.5 | F90: =E90*$B$5*(1+$B$6) -> 30550 | G90: =F90*$B$7 -> 76375 | H90: =G90-F90 -> 45825 | I90: =H90/G90 -> 0.6
A91: Al Wataniah | B91: AL WATANIAH ROWAN ELAN EDP 100ML | C91: 100 | D91: Árabe | E91: 23.5 | F91: =E91*$B$5*(1+$B$6) -> 30550 | G91: =F91*$B$7 -> 76375 | H91: =G91-F91 -> 45825 | I91: =H91/G91 -> 0.6
... A100: Al Wataniah | B100: AL WATANIAH WATANI PINK EDP 100ML FEMININO | C100: 100 | D100: Árabe | E100: 25.5 | F100: =E100*$B$5*(1+$B$6) -> 33150 | G100: =F100*$B$7 -> 82875 | H100: =G100-F100 -> 49725 | I100: =H100/G100 -> 0.6
A101: Al Wataniah | B101: Ameeri EDP | C101: 100 | D101: Árabe | E101: 10 | F101: =E101*$B$5*(1+$B$6) -> 13000 | G101: =F101*$B$7 -> 32500 | H101: =G101-F101 -> 19500 | I101: =H101/G101 -> 0.6 | K101: Entrada de gama, muy barato
A102: Al Wataniah | B102: Amnia EDP (fem) | C102: 100 | D102: Árabe | E102: 14 | F102: =E102*$B$5*(1+$B$6) -> 18200 | G102: =F102*$B$7 -> 45500 | H102: =G102-F102 -> 27300 | I102: =H102/G102 -> 0.6
A103: Al Wataniah | B103: Attar Al Wesal EDP | C103: 100 | D103: Árabe | E103: 12 | F103: =E103*$B$5*(1+$B$6) -> 15600 | G103: =F103*$B$7 -> 39000 | H103: =G103-F103 -> 23400 | I103: =H103/G103 -> 0.6
A104: Al Wataniah | B104: Bareeq Al Dhahab EDP | C104: 100 | D104: Árabe | E104: 10 | F104: =E104*$B$5*(1+$B$6) -> 13000 | G104: =F104*$B$7 -> 32500 | H104: =G104-F104 -> 19500 | I104: =H104/G104 -> 0.6
A105: Al Wataniah | B105: Sabah Al Ward Delilah EDP (fem) | C105: 100 | D105: Árabe | E105: 23.5 | F105: =E105*$B$5*(1+$B$6) -> 30550 | G105: =F105*$B$7 -> 76375 | H105: =G105-F105 -> 45825 | I105: =H105/G105 -> 0.6
A106: Al Wataniah | B106: Sultan Al Lail EDP | C106: 100 | D106: Árabe | E106: 11 | F106: =E106*$B$5*(1+$B$6) -> 14300 | G106: =F106*$B$7 -> 35750 | H106: =G106-F106 -> 21450 | I106: =H106/G106 -> 0.6
A107: Al Wataniah | B107: Watani Purple EDP (fem) | C107: 100 | D107: Árabe | E107: 13 | F107: =E107*$B$5*(1+$B$6) -> 16900 | G107: =F107*$B$7 -> 42250 | H107: =G107-F107 -> 25350 | I107: =H107/G107 -> 0.6
A108: Alexandre J | B108: ALEXANDRE J ORIENTAL ENIGMA EDP 100ML UNISEX | C108: 100 | D108: Nicho | E108: 240 | F108: =E108*$B$5*(1+$B$6) -> 312000 | G108: =F108*$B$7 -> 780000 | H108: =G108-F108 -> 468000 | I108: =H108/G108 -> 0.6
A109: Alexandre J | B109: ALEXANDRE J PASSION BLISS EDP 100ML UNISEX | C109: 100 | D109: Nicho | E109: 75 | F109: =E109*$B$5*(1+$B$6) -> 97500 | G109: =F109*$B$7 -> 243750 | H109: =G109-F109 -> 146250 | I109: =H109/G109 -> 0.6
A110: Alexandre J | B110: ALEXANDRE J ROSE OUD EDP 100ML FEM | C110: 100 | D110: Nicho | E110: 42 | F110: =E110*$B$5*(1+$B$6) -> 54600 | G110: =F110*$B$7 -> 136500 | H110: =G110-F110 -> 81900 | I110: =H110/G110 -> 0.6
A111: Alfred Ritchy | B111: ALFRED RITCHY ANATOLIA EDP 100ML UNISEX | C111: 100 | D111: Nicho | E111: 100 | F111: =E111*$B$5*(1+$B$6) -> 130000 | G111: =F111*$B$7 -> 325000 | H111: =G111-F111 -> 195000 | I111: =H111/G111 -> 0.6
A112: Alfred Ritchy | B112: ALFRED RITCHY DACHA EDP 100ML UNISEX | C112: 100 | D112: Nicho | E112: 100 | F112: =E112*$B$5*(1+$B$6) -> 130000 | G112: =F112*$B$7 -> 325000 | H112: =G112-F112 -> 195000 | I112: =H112/G112 -> 0.6
A113: Alfred Ritchy | B113: ALFRED RITCHY JETTY EDP 100ML UNISEX | C113: 100 | D113: Nicho | E113: 100 | F113: =E113*$B$5*(1+$B$6) -> 130000 | G113: =F113*$B$7 -> 325000 | H113: =G113-F113 -> 195000 | I113: =H113/G113 -> 0.6
... A145: Antonio Banderas | B145: ANTONIO BANDERAS THE SECRET MEN 200ML EDT MASC | C145: 200 | D145: Diseñador | E145: 18.5 | F145: =E145*$B$5*(1+$B$6) -> 24050 | G145: =F145*$B$7 -> 60125 | H145: =G145-F145 -> 36075 | I145: =H145/G145 -> 0.6
A146: Antonio Banderas | B146: Blue Seduction EDT | C146: 200 | D146: Diseñador | E146: 18.9 | F146: =E146*$B$5*(1+$B$6) -> 24570 | G146: =F146*$B$7 -> 61425 | H146: =G146-F146 -> 36855 | I146: =H146/G146 -> 0.6 | K146: 200ml, muy económico
A147: Antonio Banderas | B147: Queen of Seduction EDT (fem) | C147: 80 | D147: Diseñador | E147: 15.9 | F147: =E147*$B$5*(1+$B$6) -> 20670 | G147: =F147*$B$7 -> 51675 | H147: =G147-F147 -> 31005 | I147: =H147/G147 -> 0.6 | K147: Bajo costo, alta rotación
A148: Antonio Banderas | B148: TESTER ANTONIO BANDERAS BLUE SEDUCTION EDT 100ML MAS | C148: 100 | D148: Tester | E148: 12 | F148: =E148*$B$5*(1+$B$6) -> 15600 | G148: =F148*$B$7 -> 39000 | H148: =G148-F148 -> 23400 | I148: =H148/G148 -> 0.6
A149: Antonio Banderas | B149: TESTER ANTONIO BANDERAS BLUE SEDUCTION EDT 80ML FEM | C149: 80 | D149: Tester | E149: 12 | F149: =E149*$B$5*(1+$B$6) -> 15600 | G149: =F149*$B$7 -> 39000 | H149: =G149-F149 -> 23400 | I149: =H149/G149 -> 0.6
A150: Antonio Banderas | B150: TESTER ANTONIO BANDERAS GOLDEN SECRET 100ML MASC | C150: 100 | D150: Tester | E150: 12 | F150: =E150*$B$5*(1+$B$6) -> 15600 | G150: =F150*$B$7 -> 39000 | H150: =G150-F150 -> 23400 | I150: =H150/G150 -> 0.6
A151: Antonio Banderas | B151: TESTER ANTONIO BANDERAS HER GOLDEN SECRET EDT 80ML FEM | C151: 80 | D151: Tester | E151: 12 | F151: =E151*$B$5*(1+$B$6) -> 15600 | G151: =F151*$B$7 -> 39000 | H151: =G151-F151 -> 23400 | I151: =H151/G151 -> 0.6
A152: Antonio Banderas | B152: TESTER ANTONIO BANDERAS SECRET ABSOLU EDT 100ML | C152: 100 | D152: Tester | E152: 15 | F152: =E152*$B$5*(1+$B$6) -> 19500 | G152: =F152*$B$7 -> 48750 | H152: =G152-F152 -> 29250 | I152: =H152/G152 -> 0.6
A153: Antonio Banderas | B153: TESTER ANTONIO BANDERAS SECRET EDT 100ML | C153: 100 | D153: Tester | E153: 11 | F153: =E153*$B$5*(1+$B$6) -> 14300 | G153: =F153*$B$7 -> 35750 | H153: =G153-F153 -> 21450 | I153: =H153/G153 -> 0.6
A154: Antonio Banderas | B154: TESTER ANTONIO BANDERAS SEDUCTION IN BLACK EDT 100ML | C154: 100 | D154: Tester | E154: 11 | F154: =E154*$B$5*(1+$B$6) -> 14300 | G154: =F154*$B$7 -> 35750 | H154: =G154-F154 -> 21450 | I154: =H154/G154 -> 0.6
A155: Antonio Banderas | B155: TESTER ANTONIO BANDERAS THE ICON SUPREME EDP 100ML FEM | C155: 100 | D155: Tester | E155: 18 | F155: =E155*$B$5*(1+$B$6) -> 23400 | G155: =F155*$B$7 -> 58500 | H155: =G155-F155 -> 35100 | I155: =H155/G155 -> 0.6
A156: Antonio Banderas | B156: The Icon Red EDP (fem) | C156: 100 | D156: Diseñador | E156: 19 | F156: =E156*$B$5*(1+$B$6) -> 24700 | G156: =F156*$B$7 -> 61750 | H156: =G156-F156 -> 37050 | I156: =H156/G156 -> 0.6
A157: Arabian Oud | B157: ARABIAN OUD ARABIAN KNIGHT EDP 100ML MASC | C157: 100 | D157: Árabe | E157: 180 | F157: =E157*$B$5*(1+$B$6) -> 234000 | G157: =F157*$B$7 -> 585000 | H157: =G157-F157 -> 351000 | I157: =H157/G157 -> 0.6
A158: Arabian Oud | B158: ARABIAN OUD MADAWI EDP 90ML FEM | C158: 90 | D158: Árabe | E158: 210 | F158: =E158*$B$5*(1+$B$6) -> 273000 | G158: =F158*$B$7 -> 682500 | H158: =G158-F158 -> 409500 | I158: =H158/G158 -> 0.6
A159: Ard Al Zaafaran | B159: ARD AL ZAAFARAN BODY CREAM ASAD 280G | D159: Árabe | E159: 13.5 | F159: =E159*$B$5*(1+$B$6) -> 17550 | G159: =F159*$B$7 -> 43875 | H159: =G159-F159 -> 26325 | I159: =H159/G159 -> 0.6
A160: Ard Al Zaafaran | B160: ARD AL ZAAFARAN BODY CREAM YARA 310G | D160: Árabe | E160: 15 | F160: =E160*$B$5*(1+$B$6) -> 19500 | G160: =F160*$B$7 -> 48750 | H160: =G160-F160 -> 29250 | I160: =H160/G160 -> 0.6
A161: Armaf | B161: ARMAF BON BON DELIGHTS EDP 100ML | C161: 100 | D161: Árabe | E161: 40 | F161: =E161*$B$5*(1+$B$6) -> 52000 | G161: =F161*$B$7 -> 130000 | H161: =G161-F161 -> 78000 | I161: =H161/G161 -> 0.6
A162: Armaf | B162: ARMAF CLUB DE NUIT BLING EDP 75ML | C162: 75 | D162: Árabe | E162: 33.9 | F162: =E162*$B$5*(1+$B$6) -> 44070 | G162: =F162*$B$7 -> 110175 | H162: =G162-F162 -> 66105 | I162: =H162/G162 -> 0.6
A163: Armaf | B163: ARMAF CLUB DE NUIT ICONIC (BLUE) EDP 105ML | C163: 105 | D163: Árabe | E163: 28 | F163: =E163*$B$5*(1+$B$6) -> 36400 | G163: =F163*$B$7 -> 91000 | H163: =G163-F163 -> 54600 | I163: =H163/G163 -> 0.6
A164: Armaf | B164: ARMAF CLUB DE NUIT INTENSE MAN EDP 200ML | C164: 200 | D164: Árabe | E164: 46 | F164: =E164*$B$5*(1+$B$6) -> 59800 | G164: =F164*$B$7 -> 149500 | H164: =G164-F164 -> 89700 | I164: =H164/G164 -> 0.6
A165: Armaf | B165: ARMAF CLUB DE NUIT INTENSE MAN EDT 105ML | C165: 105 | D165: Árabe | E165: 25 | F165: =E165*$B$5*(1+$B$6) -> 32500 | G165: =F165*$B$7 -> 81250 | H165: =G165-F165 -> 48750 | I165: =H165/G165 -> 0.6
A166: Armaf | B166: ARMAF CLUB DE NUIT LIONHEART MAN EDP 100ML MASCULINO | C166: 100 | D166: Árabe | E166: 29 | F166: =E166*$B$5*(1+$B$6) -> 37700 | G166: =F166*$B$7 -> 94250 | H166: =G166-F166 -> 56550 | I166: =H166/G166 -> 0.6
A167: Armaf | B167: ARMAF CLUB DE NUIT LIONHEART WOMAN EDP 100ML FEMININO | C167: 100 | D167: Árabe | E167: 24 | F167: =E167*$B$5*(1+$B$6) -> 31200 | G167: =F167*$B$7 -> 78000 | H167: =G167-F167 -> 46800 | I167: =H167/G167 -> 0.6
A168: Armaf | B168: ARMAF CLUB DE NUIT MILESTONE EDP 105ML | C168: 105 | D168: Árabe | E168: 22.75 | F168: =E168*$B$5*(1+$B$6) -> 29575 | G168: =F168*$B$7 -> 73937.5 | H168: =G168-F168 -> 44362.5 | I168: =H168/G168 -> 0.6
A169: Armaf | B169: ARMAF CLUB DE NUIT PRECIEUX I EDP 55ML | C169: 55 | D169: Árabe | E169: 35 | F169: =E169*$B$5*(1+$B$6) -> 45500 | G169: =F169*$B$7 -> 113750 | H169: =G169-F169 -> 68250 | I169: =H169/G169 -> 0.6
A170: Armaf | B170: ARMAF CLUB DE NUIT PRECIEUX IV EXT 55ML | C170: 55 | D170: Árabe | E170: 41.25 | F170: =E170*$B$5*(1+$B$6) -> 53625 | G170: =F170*$B$7 -> 134062.5 | H170: =G170-F170 -> 80437.5 | I170: =H170/G170 -> 0.6
A171: Armaf | B171: ARMAF CLUB DE NUIT SILLAGE EDP 105ML | C171: 105 | D171: Árabe | E171: 24.5 | F171: =E171*$B$5*(1+$B$6) -> 31850 | G171: =F171*$B$7 -> 79625 | H171: =G171-F171 -> 47775 | I171: =H171/G171 -> 0.6
A172: Armaf | B172: ARMAF CLUB DE NUIT UNTOLD EDP 105ML | C172: 105 | D172: Árabe | E172: 26.9 | F172: =E172*$B$5*(1+$B$6) -> 34970 | G172: =F172*$B$7 -> 87425 | H172: =G172-F172 -> 52455 | I172: =H172/G172 -> 0.6
... A194: Armaf | B194: ARMAF RED SKY EDP 105ML | C194: 105 | D194: Árabe | E194: 25 | F194: =E194*$B$5*(1+$B$6) -> 32500 | G194: =F194*$B$7 -> 81250 | H194: =G194-F194 -> 48750 | I194: =H194/G194 -> 0.6
A195: Armaf | B195: Club de Nuit Man EDT | C195: 105 | D195: Árabe | E195: 20.5 | F195: =E195*$B$5*(1+$B$6) -> 26650 | G195: =F195*$B$7 -> 66625 | H195: =G195-F195 -> 39975 | I195: =H195/G195 -> 0.6 | J195: 57000 | K195: Bestseller en AR (Intense Man, +50mil vend.) ~$55-75k
A196: Armaf | B196: DESODORANTE ARMAF CLUB DE NUIT WOMAN INTENSE 200ML | C196: 200 | D196: Árabe | E196: 3.25 | F196: =E196*$B$5*(1+$B$6) -> 4225 | G196: =F196*$B$7 -> 10562.5 | H196: =G196-F196 -> 6337.5 | I196: =H196/G196 -> 0.6
A197: Armaf | B197: DESODORANTE ARMAF HOMME FOR MEN 200ML | C197: 200 | D197: Árabe | E197: 3 | F197: =E197*$B$5*(1+$B$6) -> 3900 | G197: =F197*$B$7 -> 9750 | H197: =G197-F197 -> 5850 | I197: =H197/G197 -> 0.6
A198: Armaf | B198: DESODORANTE ARMAF LE PARFAIT PANACHE POUR FEMME 200ML | C198: 200 | D198: Árabe | E198: 3 | F198: =E198*$B$5*(1+$B$6) -> 3900 | G198: =F198*$B$7 -> 9750 | H198: =G198-F198 -> 5850 | I198: =H198/G198 -> 0.6
A199: Armaf | B199: DESODORANTE ARMAF ODYSSEY AOUD 200ML | C199: 200 | D199: Árabe | E199: 3 | F199: =E199*$B$5*(1+$B$6) -> 3900 | G199: =F199*$B$7 -> 9750 | H199: =G199-F199 -> 5850 | I199: =H199/G199 -> 0.6
A200: Armaf | B200: DESODORANTE ARMAF ODYSSEY CHOCOLATE 200ML | C200: 200 | D200: Árabe | E200: 2.75 | F200: =E200*$B$5*(1+$B$6) -> 3575 | G200: =F200*$B$7 -> 8937.5 | H200: =G200-F200 -> 5362.5 | I200: =H200/G200 -> 0.6
A201: Armaf | B201: DESODORANTE ARMAF TAG HER FOR WOMEN 200ML | C201: 200 | D201: Árabe | E201: 3 | F201: =E201*$B$5*(1+$B$6) -> 3900 | G201: =F201*$B$7 -> 9750 | H201: =G201-F201 -> 5850 | I201: =H201/G201 -> 0.6
...

Sheet Resumen por marca
A1: Marca | B1: # productos | C1: Costo USD mín | D1: Costo USD máx | E1: Costo USD promedio | F1: Margen % promedio
A2: Lattafa | B2: =COUNTIF(Modelo!$A$10:$A$1922,$A2) -> 151 | C2: =MINIFS(Modelo!$E$10:$E$1922,Modelo!$A$10:$A$1922,$A2) -> 2.75 | D2: =MAXIFS(Modelo!$E$10:$E$1922,Modelo!$A$10:$A$1922,$A2) -> 43 | E2: =AVERAGEIF(Modelo!$A$10:$A$1922,$A2,Modelo!$E$10:$E$1922) -> 17.512517 | F2: =AVERAGEIF(Modelo!$A$10:$A$1922,$A2,Modelo!$I$10:$I$1922) -> 0.6
A3: Maison Alhambra | B3: =COUNTIF(Modelo!$A$10:$A$1922,$A3) -> 127 | C3: =MINIFS(Modelo!$E$10:$E$1922,Modelo!$A$10:$A$1922,$A3) -> 2.7 | D3: =MAXIFS(Modelo!$E$10:$E$1922,Modelo!$A$10:$A$1922,$A3) -> 24 | E3: =AVERAGEIF(Modelo!$A$10:$A$1922,$A3,Modelo!$E$10:$E$1922) -> 10.33315 | F3: =AVERAGEIF(Modelo!$A$10:$A$1922,$A3,Modelo!$I$10:$I$1922) -> 0.6
A4: Carolina Herrera | B4: =COUNTIF(Modelo!$A$10:$A$1922,$A4) -> 83 | C4: =MINIFS(Modelo!$E$10:$E$1922,Modelo!$A$10:$A$1922,$A4) -> 41 | D4: =MAXIFS(Modelo!$E$10:$E$1922,Modelo!$A$10:$A$1922,$A4) -> 98 | E4: =AVERAGEIF(Modelo!$A$10:$A$1922,$A4,Modelo!$E$10:$E$1922) -> 65.699398 | F4: =AVERAGEIF(Modelo!$A$10:$A$1922,$A4,Modelo!$I$10:$I$1922) -> 0.6
A5: Paco Rabanne | B5: =COUNTIF(Modelo!$A$10:$A$1922,$A5) -> 61 | C5: =MINIFS(Modelo!$E$10:$E$1922,Modelo!$A$10:$A$1922,$A5) -> 28 | D5: =MAXIFS(Modelo!$E$10:$E$1922,Modelo!$A$10:$A$1922,$A5) -> 115 | E5: =AVERAGEIF(Modelo!$A$10:$A$1922,$A5,Modelo!$E$10:$E$1922) -> 67.024426 | F5: =AVERAGEIF(Modelo!$A$10:$A$1922,$A5,Modelo!$I$10:$I$1922) -> 0.6
A6: Al Haramain | B6: =COUNTIF(Modelo!$A$10:$A$1922,$A6) -> 57 | C6: =MINIFS(Modelo!$E$10:$E$1922,Modelo!$A$10:$A$1922,$A6) -> 11 | D6: =MAXIFS(Modelo!$E$10:$E$1922,Modelo!$A$10:$A$1922,$A6) -> 130 | E6: =AVERAGEIF(Modelo!$A$10:$A$1922,$A6,Modelo!$E$10:$E$1922) -> 43.631404 | F6: =AVERAGEIF(Modelo!$A$10:$A$1922,$A6,Modelo!$I$10:$I$1922) -> 0.6
A7: Chanel | B7: =COUNTIF(Modelo!$A$10:$A$1922,$A7) -> 44 | C7: =MINIFS(Modelo!$E$10:$E$1922,Modelo!$A$10:$A$1922,$A7) -> 82 | D7: =MAXIFS(Modelo!$E$10:$E$1922,Modelo!$A$10:$A$1922,$A7) -> 265 | E7: =AVERAGEIF(Modelo!$A$10:$A$1922,$A7,Modelo!$E$10:$E$1922) -> 135.96591 | F7: =AVERAGEIF(Modelo!$A$10:$A$1922,$A7,Modelo!$I$10:$I$1922) -> 0.6
A8: Armaf | B8: =COUNTIF(Modelo!$A$10:$A$1922,$A8) -> 43 | C8: =MINIFS(Modelo!$E$10:$E$1922,Modelo!$A$10:$A$1922,$A8) -> 2.75 | D8: =MAXIFS(Modelo!$E$10:$E$1922,Modelo!$A$10:$A$1922,$A8) -> 50 | E8: =AVERAGEIF(Modelo!$A$10:$A$1922,$A8,Modelo!$E$10:$E$1922) -> 21.42093 | F8: =AVERAGEIF(Modelo!$A$10:$A$1922,$A8,Modelo!$I$10:$I$1922) -> 0.6
A9: Dolce & Gabbana | B9: =COUNTIF(Modelo!$A$10:$A$1922,$A9) -> 43 | C9: =MINIFS(Modelo!$E$10:$E$1922,Modelo!$A$10:$A$1922,$A9) -> 38 | D9: =MAXIFS(Modelo!$E$10:$E$1922,Modelo!$A$10:$A$1922,$A9) -> 95 | E9: =AVERAGEIF(Modelo!$A$10:$A$1922,$A9,Modelo!$E$10:$E$1922) -> 58.730233 | F9: =AVERAGEIF(Modelo!$A$10:$A$1922,$A9,Modelo!$I$10:$I$1922) -> 0.6
A10: Giorgio Armani | B10: =COUNTIF(Modelo!$A$10:$A$1922,$A10) -> 43 | C10: =MINIFS(Modelo!$E$10:$E$1922,Modelo!$A$10:$A$1922,$A10) -> 18 | D10: =MAXIFS(Modelo!$E$10:$E$1922,Modelo!$A$10:$A$1922,$A10) -> 330 | E10: =AVERAGEIF(Modelo!$A$10:$A$1922,$A10,Modelo!$E$10:$E$1922) -> 83.24186 | F10: =AVERAGEIF(Modelo!$A$10:$A$1922,$A10,Modelo!$I$10:$I$1922) -> 0.6
A11: Creed | B11: =COUNTIF(Modelo!$A$10:$A$1922,$A11) -> 41 | C11: =MINIFS(Modelo!$E$10:$E$1922,Modelo!$A$10:$A$1922,$A11) -> 195 | D11: =MAXIFS(Modelo!$E$10:$E$1922,Modelo!$A$10:$A$1922,$A11) -> 525 | E11: =AVERAGEIF(Modelo!$A$10:$A$1922,$A11,Modelo!$E$10:$E$1922) -> 275.90244 | F11: =AVERAGEIF(Modelo!$A$10:$A$1922,$A11,Modelo!$I$10:$I$1922) -> 0.6
A12: Jean Paul Gaultier | B12: =COUNTIF(Modelo!$A$10:$A$1922,$A12) -> 40 | C12: =MINIFS(Modelo!$E$10:$E$1922,Modelo!$A$10:$A$1922,$A12) -> 44 | D12: =MAXIFS(Modelo!$E$10:$E$1922,Modelo!$A$10:$A$1922,$A12) -> 115 | E12: =AVERAGEIF(Modelo!$A$10:$A$1922,$A12,Modelo!$E$10:$E$1922) -> 78.41 | F12: =AVERAGEIF(Modelo!$A$10:$A$1922,$A12,Modelo!$I$10:$I$1922) -> 0.6
A13: Givenchy | B13: =COUNTIF(Modelo!$A$10:$A$1922,$A13) -> 39 | C13: =MINIFS(Modelo!$E$10:$E$1922,Modelo!$A$10:$A$1922,$A13) -> 36 | D13: =MAXIFS(Modelo!$E$10:$E$1922,Modelo!$A$10:$A$1922,$A13) -> 110 | E13: =AVERAGEIF(Modelo!$A$10:$A$1922,$A13,Modelo!$E$10:$E$1922) -> 70.798718 | F13: =AVERAGEIF(Modelo!$A$10:$A$1922,$A13,Modelo!$I$10:$I$1922) -> 0.6
... A139: Tubbees | B139: =COUNTIF(Modelo!$A$10:$A$1922,$A139) -> 1 | C139: =MINIFS(Modelo!$E$10:$E$1922,Modelo!$A$10:$A$1922,$A139) -> 7.25 | D139: =MAXIFS(Modelo!$E$10:$E$1922,Modelo!$A$10:$A$1922,$A139) -> 7.25 | E139: =AVERAGEIF(Modelo!$A$10:$A$1922,$A139,Modelo!$E$10:$E$1922) -> 7.25 | F139: =AVERAGEIF(Modelo!$A$10:$A$1922,$A139,Modelo!$I$10:$I$1922) -> 0.6
A140: (TODAS LAS MARCAS) | B140: =SUM(B2:B139) -> 1913 | C140: =MIN(Modelo!$E$10:$E$1922) -> 2.7 | D140: =MAX(Modelo!$E$10:$E$1922) -> 525 | E140: =AVERAGE(Modelo!$E$10:$E$1922) -> 74.243236 | F140: =AVERAGE(Modelo!$I$10:$I$1922) -> 0.6

Sheet Notas
A1: NOTAS Y METODOLOGÍA
A3: Cómo usar este modelo:
A4: 1. Cargá la cotización real del dólar con el que compran (celda B5). Es el dato que más mueve los márgenes.
A5: 2. El 'Costo de traída %' (B6) está en 0 por ahora. Cuando definan el costo/riesgo de traer la mercadería, lo ponen ahí y todo se recalcula.
A6: 3. El 'Markup objetivo' (B7) define el PVP sugerido (PVP = costo x markup). Ajustalo según la categoría o editá el PVP fila por fila.
A7: 4. La columna 'Precio mercado AR' es referencia para chequear que el PVP sugerido sea competitivo (no es un cálculo).
A9: Origen de los datos:
A10: - Costos USD: precios de lista del sitio del proveedor Star Company (base.fluxoigm.com / starcompany-py.com), categoría Perfumes, junio 2026.
A11: - Precios de mercado AR: búsquedas en Mercado Libre y perfumerías online argentinas, junio 2026. Son rangos orientativos, no precios fijos.
A13: Limitaciones a tener en cuenta:
A14: - Las páginas del proveedor por marca no exponen precio público; los costos cargados salen del listado general y de carruseles de productos. Faltan SKUs (ej. Lattafa Yara/Khamrah) cuyo precio no se pudo leer todavía.
A15: - Para ampliar: si el proveedor te pasa una lista (CSV/planilla) o pantallazos por marca, se agregan filas y el modelo escala solo.
... A18: - Si obtienen rebajas por mayorista, actualizar la columna 'Costo USD' (azul) y los márgenes se recalculan.
